[
  {
    "title": "Home",
    "name": "dashboard",
    "is_heading": false,
    "is_active": false,
    "link": "/dashboard",
    "class_name": "",
    "is_icon_class": true,
    "icon": "ri-home-4-line"
  },
  {
    "title": "Clientes",
    "name": "clientes",
    "is_heading": false,
    "is_active": false,
    "link": "/clientes",
    "class_name": "",
    "is_icon_class": true,
    "icon": "ri-user-4-line"
  },
  {
    "title": "Produtos",
    "name": "produtos",
    "is_heading": false,
    "is_active": false,
    "link": "/produtos",
    "class_name": "",
    "is_icon_class": true,
    "icon": "ri-briefcase-4-line"
  },
  {
    "title": "Conta Bancaria",
    "name": "Conta Bancaria",
    "is_heading": false,
    "is_active": false,
    "link": "/conta-bancaria",
    "class_name": "",
    "is_icon_class": true,
    "icon": "ri-briefcase-4-line"
  },
  {
    "title": "Extrato",
    "name": "Extrato",
    "is_heading": false,
    "is_active": false,
    "link": "/extrato",
    "class_name": "",
    "is_icon_class": true,
    "icon": "ri-briefcase-4-line"
  },
  {
    "title": "Financeiro",
    "name": "Financeiro",
    "is_heading": false,
    "is_active": false,
    "link": "/financeiro",
    "class_name": "",
    "is_icon_class": true,
    "icon": "ri-briefcase-4-line"
  },
  {
    "title": "Fornecedores",
    "name": "Fornecedores",
    "is_heading": false,
    "is_active": false,
    "class_name": "",
    "is_icon_class": true,
    "icon": "ri-edit-line",
    "children": [
      {
        "title": "Adicionar Fornecedor",
        "is_active": false,
        "link": "/relatorio/contrato",
        "class_name": "",
        "is_icon_class": true,
        "icon": "ri-edit-line"
      },
      {
        "title": "Serviços",
        "is_active": false,
        "link": "/relatorio/parceiro",
        "class_name": "",
        "is_icon_class": true,
        "icon": "ri-edit-line"
      }
    ]
  },
  {
    "title": "Relatorios",
    "name": "relatorios",
    "is_heading": false,
    "is_active": false,
    "class_name": "",
    "is_icon_class": true,
    "icon": "ri-edit-line",
    "children": [
      {
        "title": "Contratos",
        "is_active": false,
        "link": "/relatorio/contrato",
        "class_name": "",
        "is_icon_class": true,
        "icon": "ri-edit-line"
      },
      {
        "title": "Parceiros",
        "is_active": false,
        "link": "/relatorio/parceiro",
        "class_name": "",
        "is_icon_class": true,
        "icon": "ri-edit-line"
      },
      {
        "title": "Analistas",
        "is_active": false,
        "link": "/relatorio/analistas",
        "class_name": "",
        "is_icon_class": true,
        "icon": "ri-edit-line"
      }
    ]
  }
  
]
